MANIFEST.in
README.rst
setup.py
src/bookie_api/__init__.py
src/bookie_api/api.py
src/bookie_api/client.py
src/bookie_api/commands.py
src/bookie_api.egg-info/PKG-INFO
src/bookie_api.egg-info/SOURCES.txt
src/bookie_api.egg-info/dependency_links.txt
src/bookie_api.egg-info/entry_points.txt
src/bookie_api.egg-info/not-zip-safe
src/bookie_api.egg-info/requires.txt
src/bookie_api.egg-info/top_level.txt
src/bookie_api/tests/__init__.py