Metadata-Version: 1.0
Name: bookie-api
Version: 0.4.7
Summary: Api and command line client for Bookie
Home-page: http://docs.bmark.us
Author: Rick Harding
Author-email: rharding@mitechie.com
License: AGPL
Keywords: bookmarks api client command line
Platform: UNKNOWN
